setup.py
nuuz_probability/BinomialDistribution.py
nuuz_probability/GaussianDistribution.py
nuuz_probability/GeneralDistribution.py
nuuz_probability/__init__.py
nuuz_probability.egg-info/PKG-INFO
nuuz_probability.egg-info/SOURCES.txt
nuuz_probability.egg-info/dependency_links.txt
nuuz_probability.egg-info/not-zip-safe
nuuz_probability.egg-info/top_level.txt