Metadata-Version: 2.1
Name: nuuz-probability
Version: 1.2
Summary: Gaussian and Binomial distributions
Home-page: UNKNOWN
Author: Doston Kholdarov
Author-email: roostamovic@yahoo.com
License: UNKNOWN
Platform: UNKNOWN
